java_gradescope_autograder_helper/__init__.py
java_gradescope_autograder_helper/cli.py
java_gradescope_autograder_helper/compiler.py
java_gradescope_autograder_helper/helpers.py
java_gradescope_autograder_helper/init_autograder.py
java_gradescope_autograder_helper/loader.py
java_gradescope_autograder_helper/run_autograder.py
java_gradescope_autograder_helper/test_runner.py
java_gradescope_autograder_helper/zip_autograder.py
java_gradescope_autograder_helper/checkstyle/__init__.py
java_gradescope_autograder_helper/checkstyle/bowdoin_checks.xml
java_gradescope_autograder_helper/checkstyle/checkstyle-10.21.2-all.jar
java_gradescope_autograder_helper/checkstyle/checkstyle.py
java_gradescope_autograder_helper/examples/autograder/run_autograder
java_gradescope_autograder_helper/examples/autograder/results/results.json
java_gradescope_autograder_helper/examples/autograder/source/run_autograder
java_gradescope_autograder_helper/examples/autograder/source/setup.sh
java_gradescope_autograder_helper/examples/autograder/source/tests.py
java_gradescope_autograder_helper/examples/autograder/source/reference_solution/Main.java
java_gradescope_autograder_helper/examples/autograder/submission/Main.java
java_gradescope_autograder_helper-1.2.9.1.dist-info/METADATA
java_gradescope_autograder_helper-1.2.9.1.dist-info/WHEEL
java_gradescope_autograder_helper-1.2.9.1.dist-info/entry_points.txt
java_gradescope_autograder_helper-1.2.9.1.dist-info/licenses/LICENSE
java_gradescope_autograder_helper-1.2.9.1.dist-info/RECORD
