Metadata-Version: 2.4
Name: java-gradescope-autograder-helper
Version: 1.2.9.1
Summary: A helper package for setting up Gradescope autograder tests for Java projects
Author-email: Rafael Almeida <github@ralmeida.dev>
License: Copyright © 2025 Rafael Almeida. All Rights Reserved.
License-File: LICENSE
Requires-Python: >=3.10
